cybersentinel/__init__.py
cybersentinel/checker.py
cybersentinel/malware_check.py
cybersentinel/tempCodeRunnerFile.py
cybersentinel-0.2.2.dist-info/LICENSE
cybersentinel-0.2.2.dist-info/METADATA
cybersentinel-0.2.2.dist-info/WHEEL
cybersentinel-0.2.2.dist-info/entry_points.txt
cybersentinel-0.2.2.dist-info/top_level.txt
cybersentinel-0.2.2.dist-info/RECORD
