Metadata-Version: 2.2
Name: CyberSentinel
Version: 0.2.2
Summary: A Website Security & Health Checker
Author: Ansh Garg
License: MIT
Classifier: Programming Language :: Python :: 3
Classifier: License :: OSI Approved :: MIT License
Classifier: Operating System :: OS Independent
Requires-Python: >=3.6
License-File: LICENSE
Requires-Dist: requests
